[
  {
    "id": 1,
    "name": "Home",
    "content1": "Seorang profesional progammer dengan keahlian sebagai full-stack developer, desainer UI/UX, dan system analyst",
    "content2": "berpengalaman dalam mengembangkan aplikasi berbasis website, menciptakan antarmuka yang intuitif, serta menganalisis kebutuhan untuk menghasilkan solusi yang efektif dan inovatif",
    "image": "pexels-gleb-lucky-77753534-9109231.jpg"
  },
  {
    "id": 2,
    "name": "About",
    "content1": "Muhammad Azka Nuril Islami as KostsPlayer, berasal dari Metropolitan Lumajang, Jawa Timur, Indonesia",
    "content2": "menempuh pendidikan Diploma IV di Universitas Logistik & Bisnis Internasional (ULBI), Bandung, Indonesia",
    "image": "pexels-ionela-mat-268382825-27180805.jpg"
  },
  {
    "id": 3,
    "name": "Skills",
    "content1": "React, JavaScript, HTML, CSS, SCSS, Node.js, Express, CodeIgniter 3/4, MySQL, MongoDB, Supabase, Git, Github, Vercel",
    "content2": "10 USD/hour and make a deal for your dream project",
    "image": "pexels-pixabay-210158.jpg"
  },
  {
    "id": 4,
    "name": "Contact",
    "content1": [
      {
        "name": "Email"
      },
      {
        "name": "Phone"
      },
      {
        "name": "Github"
      },
      {
        "name": "Instagram"
      }
    ],
    "content2": [
      {
        "name": "azka.nuril070@gmail.com"
      },
      {
        "name": "+62 823 3410 0715"
      },
      {
        "name": "KostsPlayer"
      },
      {
        "name": "aazkanuril"
      }
    ],
    "image": "pexels-thatwasowzm-2046746382-29182343.jpg"
  }
]
